stationarizer/__init__.py
stationarizer/_version.py
stationarizer/core.py
stationarizer/util.py
tests/__init__.py
tests/stochastic_process_generators.py
tests/test_simple_auto_statio.py
stationarizer-0.0.11.dist-info/LICENSE
stationarizer-0.0.11.dist-info/METADATA
stationarizer-0.0.11.dist-info/WHEEL
stationarizer-0.0.11.dist-info/top_level.txt
stationarizer-0.0.11.dist-info/RECORD
